pai/__init__.py
pai/dataset.py
pai/dsw.py
pai/estimator.py
pai/exception.py
pai/experiment.py
pai/image.py
pai/predictor.py
pai/processor.py
pai/serializers.py
pai/session.py
pai/tensorboard.py
pai/version.py
pai/api/__init__.py
pai/api/algorithm.py
pai/api/api_container.py
pai/api/base.py
pai/api/client_factory.py
pai/api/code_source.py
pai/api/dataset.py
pai/api/experiment.py
pai/api/image.py
pai/api/job.py
pai/api/lineage.py
pai/api/model.py
pai/api/pipeline.py
pai/api/pipeline_run.py
pai/api/service.py
pai/api/tensorboard.py
pai/api/training_job.py
pai/api/workspace.py
pai/common/__init__.py
pai/common/consts.py
pai/common/docker_utils.py
pai/common/git_utils.py
pai/common/logging.py
pai/common/oss_utils.py
pai/common/utils.py
pai/common/yaml_utils.py
pai/huggingface/__init__.py
pai/huggingface/estimator.py
pai/huggingface/model.py
pai/job/__init__.py
pai/job/_local_training_job.py
pai/job/_training_job.py
pai/libs/__init__.py
pai/libs/alibabacloud_aiworkspace20210204/__init__.py
pai/libs/alibabacloud_aiworkspace20210204/client.py
pai/libs/alibabacloud_aiworkspace20210204/models.py
pai/libs/alibabacloud_eas20210701/__init__.py
pai/libs/alibabacloud_eas20210701/client.py
pai/libs/alibabacloud_eas20210701/models.py
pai/libs/alibabacloud_pai_dlc20201203/__init__.py
pai/libs/alibabacloud_pai_dlc20201203/client.py
pai/libs/alibabacloud_pai_dlc20201203/models.py
pai/libs/alibabacloud_pai_dsw20220101/__init__.py
pai/libs/alibabacloud_pai_dsw20220101/client.py
pai/libs/alibabacloud_pai_dsw20220101/models.py
pai/libs/alibabacloud_paiflow20210202/__init__.py
pai/libs/alibabacloud_paiflow20210202/client.py
pai/libs/alibabacloud_paiflow20210202/models.py
pai/libs/alibabacloud_paistudio20220112/__init__.py
pai/libs/alibabacloud_paistudio20220112/client.py
pai/libs/alibabacloud_paistudio20220112/models.py
pai/model/__init__.py
pai/model/_model.py
pai/model/_model_recipe.py
pai/modelscope/__init__.py
pai/modelscope/estimator.py
pai/modelscope/model.py
pai/pipeline/__init__.py
pai-0.4.13.dist-info/LICENSE.txt
pai-0.4.13.dist-info/METADATA
pai-0.4.13.dist-info/WHEEL
pai-0.4.13.dist-info/top_level.txt
pai-0.4.13.dist-info/RECORD
